chongyu_flow/__init__.py
chongyu_flow/nn/__init__.py
chongyu_flow/nn/core.py
chongyu_flow/utils/__init__.py
chongyu_flow/utils/utilities.py
chongyu_flow-0.0.1.dist-info/LICENSE
chongyu_flow-0.0.1.dist-info/METADATA
chongyu_flow-0.0.1.dist-info/WHEEL
chongyu_flow-0.0.1.dist-info/top_level.txt
chongyu_flow-0.0.1.dist-info/RECORD
