Metadata-Version: 2.1
Name: chongyu-flow
Version: 0.0.1
Summary: This is a mini but function completed neural network framework
Home-page: UNKNOWN
Author: Chongyu Zhang
Author-email: zcyu_eternal@foxmail.com
License: UNKNOWN
Platform: UNKNOWN
Classifier: Programming Language :: Python :: 3
Classifier: License :: OSI Approved :: MIT License
Classifier: Operating System :: OS Independent
Requires-Python: >=3.6
